[
  {
    "listing": "/computacao.html",
    "items": [
      "/posts/computacao/BlobToolsKit/index.html",
      "/posts/computacao/Grafo de String e desafios na montagem/index.html",
      "/posts/computacao/Hifiasm e Genomescope na montagem do genoma/doc1.html",
      "/posts/computacao/Anotações Linux/index.html",
      "/posts/computacao/Bioinfo para neurociencia/index.html",
      "/posts/computacao/HiFiAdapterFilt and GenomeScope2/index.html",
      "/posts/computacao/Site NeuroTech/index.html",
      "/posts/computacao/THErmodynamicS Calculator/index.html",
      "/posts/computacao/Guia de estudo LaTex/index.html",
      "/posts/computacao/Extens__o para gerar PDF com normas ABNT/index.html",
      "/posts/computacao/TEMA CSS/index.html",
      "/posts/computacao/Kitty/index.html"
    ]
  },
  {
    "listing": "/biologia-molecular.html",
    "items": [
      "/posts/biologia-molecular/Trabalho de TE/index.html",
      "/posts/biologia-molecular/Trabalho de microbio aplicada1/index.html"
    ]
  },
  {
    "listing": "/estatistica.html",
    "items": []
  },
  {
    "listing": "/pibic.html",
    "items": [
      "/posts/pibic/BlobToolsKit/index.html",
      "/posts/pibic/BUSCO/index.html",
      "/posts/pibic/Grafo de String e desafios na montagem/index.html",
      "/posts/pibic/Hifiasm e Genomescope na montagem do genoma/doc1.html",
      "/posts/pibic/HiFiAdapterFilt and GenomeScope2/index.html"
    ]
  },
  {
    "listing": "/linux.html",
    "items": [
      "/posts/linux/Hifiasm e Genomescope na montagem do genoma/doc1.html",
      "/posts/linux/Anotações Linux/index.html",
      "/posts/linux/Minhas primeiras experiencias com Linux/index.html"
    ]
  },
  {
    "listing": "/neurociencia.html",
    "items": [
      "/posts/neurociencia/Bioinfo para neurociencia/index.html"
    ]
  },
  {
    "listing": "/filosofia.html",
    "items": [
      "/posts/filosofia/Chants of Sennaar/index.html"
    ]
  },
  {
    "listing": "/posts/computacao/Extensão para gerar PDF com normas ABNT/index.html",
    "items": []
  },
  {
    "listing": "/posts/computacao/Hifiasm e Genomescope na montagem do genoma/doc1.html",
    "items": []
  },
  {
    "listing": "/posts/pibic/Hifiasm e Genomescope na montagem do genoma/doc1.html",
    "items": []
  },
  {
    "listing": "/posts/linux/Hifiasm e Genomescope na montagem do genoma/doc1.html",
    "items": []
  },
  {
    "listing": "/posts/computacao/Purge_Dups/index.html",
    "items": []
  },
  {
    "listing": "/posts/pibic/Purge_Dups/index.html",
    "items": []
  },
  {
    "listing": "/posts/Genômica/Grafo de String e desafios na montagem/index.html",
    "items": []
  },
  {
    "listing": "/genomic.html",
    "items": [
      "/posts/Genômica/MitoHifi/index.html",
      "/posts/Genômica/BUSCO/index.html",
      "/posts/Genômica/Grafo de String e desafios na montagem/index.html",
      "/posts/Genômica/Hifiasm e Genomescope na montagem do genoma/doc1.html",
      "/posts/Genômica/HiFiAdapterFilt and GenomeScope2/index.html"
    ]
  },
  {
    "listing": "/posts/Genômica/HiFiAdapterFilt and GenomeScope2/index.html",
    "items": []
  },
  {
    "listing": "/posts/Genômica/BUSCO/index.html",
    "items": []
  },
  {
    "listing": "/posts/Genômica/MitoHifi/index.html",
    "items": []
  },
  {
    "listing": "/posts/computacao/BlobToolsKit/index.html",
    "items": []
  }
]